[
    {
        "couponCode": "HELLOFRESH70",
        "couponTitle": "Take 70% Off with Promo Code",
        "couponDescription": "Get a 70% discount on your purchase. Use this HelloFresh coupon code at checkout."
    },
    {
        "couponCode": "VTRS0524",
        "couponTitle": "Get $22 Off Your Order ",
        "couponDescription": "Paste this promo code at checkout and save $22 on your order. Valid for members only."
    },
    {
        "couponCode": "NQ-HCN1Y",
        "couponTitle": "Score 20% Off Your Order",
        "couponDescription": "Apply this HelloFresh promotional code to get 20% off your qualifying purchase at checkout."
    },
    {
        "couponCode": "OX-PGSZH",
        "couponTitle": "Take Up to 55% Off Any Purchase ",
        "couponDescription": "Enjoy shopping and get up to a 55% discount on any purchase when you enter this coupon code at checkout."
    },
    {
        "couponCode": "LCHF65",
        "couponTitle": "Save Up to 70% Off Sitewide with Promo Code",
        "couponDescription": "Enter this HelloFresh coupon code at checkout and get up to a 70% discount on your order."
    },
    {
        "couponCode": "HON10FB",
        "couponTitle": "Get 10 Free Meals + Free Apps For Life",
        "couponDescription": "Enjoy 10 free meals and free apps for life with this HelloFresh promo code."
    },
    {
        "couponCode": "POGSE14226",
        "couponTitle": "Save 60% Off w/ Coupon Code",
        "couponDescription": "Score 60% off with coupon"
    },
    {
        "couponCode": "HELLOFRESH65",
        "couponTitle": "Great Savings- 65% Off + Free Shipping",
        "couponDescription": "Use this promo code at checkout to save 65% and get free delivery on your first box."
    },
    {
        "couponCode": "51-1089B",
        "couponTitle": "HelloFresh Coupon: 75% Off Your Order",
        "couponDescription": "Take 75% off sitewide by adding this Hello Fresh code."
    },
    {
        "couponCode": "POGHF12483",
        "couponTitle": "HelloFresh Coupon: 40% Off",
        "couponDescription": "Enjoy 40% off orders on your cart using HelloFresh's promo code at checkout."
    },
    {
        "couponCode": "POGHF13649",
        "couponTitle": "Save 53% on Your First Box ",
        "couponDescription": "Shop at HelloFresh and get an extra 53% discount on your first box. Apply this discount code at checkout."
    },
    {
        "couponCode": "HELLO10",
        "couponTitle": "Take $10 Off Your Order",
        "couponDescription": "Enjoy $10 off when you spend $25 and more at Hello Fresh."
    },
    {
        "couponCode": "GSG70",
        "couponTitle": "Take 25% Off Your Purchase",
        "couponDescription": "Enter this HelloFresh coupon code at checkout and enjoy a 25% off on your purchase."
    },
    {
        "couponCode": "POGHF104509",
        "couponTitle": "HelloFresh Promo Code: Get Free Shipping on Any Order ",
        "couponDescription": "Redeem this promo code at checkout and save 20% on any order."
    },
    {
        "couponCode": "POGHF145159",
        "couponTitle": "HelloFresh Promo Code: 57% Off Your Order",
        "couponDescription": "Take 57% off your purchase using a promo code on your cart."
    },
    {
        "couponCode": "POGHF144068",
        "couponTitle": "Take 52% Off Your Purchase",
        "couponDescription": "Enjoy 52% off your order plus free breakfast and free shipping at Hello Fresh."
    },
    {
        "couponCode": "XN-6C7L8F19M",
        "couponTitle": "HelloFresh Coupon: $41 Off Your Order",
        "couponDescription": "Get $41 off your first box with HelloFresh. Use this coupon code and try their fresh, delicious meal kits delivered straight to your doorstep."
    },
    {
        "couponCode": "HELLOFRESH22",
        "couponTitle": "Get Free 22 Meals at Hello Fresh",
        "couponDescription": "Use this HelloFresh coupon and get 22 Free Meals Free First Box Shipping."
    },
    {
        "couponCode": "POGHF6248",
        "couponTitle": "Save 22% Off Using Code",
        "couponDescription": "Save 22% off with discount code"
    },
    {
        "couponCode": "ZY-PNVYB1QBN",
        "couponTitle": "HelloFresh Coupon: $41 Off Your Order",
        "couponDescription": "Use this HelloFresh coupon code and get $41 off your first meal kit orders. This is the perfect opportunity to try out their delicious kits."
    }
]