[
    {
        "couponCode": "WELCOME15",
        "couponTitle": "Score 15% Off First Order",
        "couponDescription": "Enter this Aveda coupon code to get 15% off your first order."
    },
    {
        "couponCode": "med",
        "couponTitle": "Get Free Gift on Any Order",
        "couponDescription": "Paste this promo code at checkout and get free gift on any order."
    },
    {
        "couponCode": "BDAYGIFT24",
        "couponTitle": "Aveda Coupon Code: Get Free Gift on Your Purchase ",
        "couponDescription": "Shop at Aveda and get free gift on your purchase. Enter this coupon code at checkout."
    },
    {
        "couponCode": "MYSTERY24",
        "couponTitle": "Aveda Coupon: Free Gift on Your Order",
        "couponDescription": "Take a free mystery gift when you purchase over $90+ with a promo code on your cart."
    },
    {
        "couponCode": "15OFF2023",
        "couponTitle": "Aveda Coupon: Take 15% Off Your Order",
        "couponDescription": "Save extra 15% on your purchase with this Aveda code."
    },
    {
        "couponCode": "SAVE25",
        "couponTitle": "Save 25% Off w/ Discount Code",
        "couponDescription": "Take 25% Discount on Your Order"
    },
    {
        "couponCode": "SMSWELCOME",
        "couponTitle": "Aveda's Coupon Code:15% Off Your Order",
        "couponDescription": "Apply this coupon at checkout and receive a 15% off on your order."
    },
    {
        "couponCode": "STUDENT",
        "couponTitle": "Aveda Discount Code: 20% Off Your Order",
        "couponDescription": "Apply 20% off Select Items on your purchase using this coupon code at Aveda."
    },
    {
        "couponCode": "bdaygift23",
        "couponTitle": "Aveda Coupon: Enjoy 25% Off All Orders",
        "couponDescription": "Apply this promo code at checkout to receive 25% off any purchase."
    },
    {
        "couponCode": "WRAP24",
        "couponTitle": "Aveda Coupon: Get a Free Ornament Gift Box with Your Order",
        "couponDescription": "Use this coupon code to score a free ornament gift box on orders over $75 at Aveda."
    },
    {
        "couponCode": "30OFF",
        "couponTitle": "Aveda Promo Code: Get 30% Off Your Order",
        "couponDescription": "Redeem this promo code at checkout and save 30% on your order."
    },
    {
        "couponCode": "FREESHIP",
        "couponTitle": "Free Shipping Using Code",
        "couponDescription": "Enjoy Free Shipping on Your Purchase"
    },
    {
        "couponCode": "25MEMBER23",
        "couponTitle": "Get $25 Off Orders $40+ with Promo Code",
        "couponDescription": "Get a $25 discount on your purchase over $40. Enter this coupon code at checkout."
    },
    {
        "couponCode": "SCALP",
        "couponTitle": "Free Gift with Purchase",
        "couponDescription": "Shop using this coupon code to receive Two Free Pramasana Samples with any order at Aveda."
    },
    {
        "couponCode": "AVGIFTWRAP",
        "couponTitle": "Get Free Gift at Aveda.",
        "couponDescription": "Grab free 2 select minis with any orders over $75 when you use the coupon code at checkout."
    },
    {
        "couponCode": "APPLEPAY",
        "couponTitle": "15% Off Your Order",
        "couponDescription": "Shop and get 15% off your purchase sitewide using a promo code on your cart."
    },
    {
        "couponCode": "GET10",
        "couponTitle": "Aveda Coupon: 10% Off All Orders",
        "couponDescription": "Apply this coupon code from Aveda to receive a 10% discount on your order."
    },
    {
        "couponCode": "04ALLURE15",
        "couponTitle": "Extra 15% Off Your Purchase",
        "couponDescription": "Save an additional 15% by applying this promo code at checkout."
    },
    {
        "couponCode": "BIRTHDAY23",
        "couponTitle": "23% Off at Aveda",
        "couponDescription": "Apply this promo code at checkout for a 23% discount on your order."
    },
    {
        "couponCode": "INVATIADV",
        "couponTitle": "Save 15% Off using Coupon Code",
        "couponDescription": "Enjoy 15% Discount on Your Order"
    }
]