[
    {
        "couponCode": "PCGAMER",
        "couponTitle": "Ewin Racing Coupon: 30% Off Your Order",
        "couponDescription": "Take 30% off gaming chairs and desk with this Ewin Racing code."
    },
    {
        "couponCode": "C20",
        "couponTitle": "Take $20 Off Your Order",
        "couponDescription": "Enjoy $20 off when you spend $99 with this Ewin Racing code."
    },
    {
        "couponCode": "DROIDLIFE",
        "couponTitle": "EwinRacing Discount Code: 30% Off Your Order",
        "couponDescription": "Simply enter this coupon code during checkout to get 30% off your select purchase."
    },
    {
        "couponCode": "MOMMYGAMERS",
        "couponTitle": "EwinRacing Coupon: 30% Off Your Purchase",
        "couponDescription": "Shop and save 30% with this promo code for storewide orders on your cart at EwinRacing."
    },
    {
        "couponCode": "UFD",
        "couponTitle": "EwinRacing Coupon Code: Take Up to 30% Off Your Purchase ",
        "couponDescription": "Enjoy up to a 30% discount on your purchase when you enter this coupon code at checkout."
    },
    {
        "couponCode": "TECHDEALS",
        "couponTitle": "EwinRacing Coupon: Up to 30% Off Your Purchase",
        "couponDescription": "Use this promo code at checkout to get up to 30% off your order."
    },
    {
        "couponCode": "L15",
        "couponTitle": "15% Off Your Order",
        "couponDescription": "Take 15% off your order sitewide using a promo code on your cart."
    },
    {
        "couponCode": "CODY",
        "couponTitle": "Up to 30% Off w/ Code",
        "couponDescription": "Buy at Ewinracing.com and save an up to 30% on your order when promo code is applied at checkout. Ends soon."
    },
    {
        "couponCode": "BRANDREWARD25",
        "couponTitle": "EwinRacing Promo Code: Get Up to 25% Off Your Order ",
        "couponDescription": "Redeem this promo code at checkout and save up to 25% on your order."
    },
    {
        "couponCode": "GAMERSRD",
        "couponTitle": "EwinRacing Promo Code: Get 30% Off Any Order",
        "couponDescription": "Take a 30% discount on all orders. Enter this coupon code at checkout."
    },
    {
        "couponCode": "KIX",
        "couponTitle": "Ewin Racing Coupon: 20% Off Your Order",
        "couponDescription": "Enjoy 20% off gaming chairs and desk at Ewin Racing."
    },
    {
        "couponCode": "KOEFFICIENT",
        "couponTitle": "Ewin Racing Coupon: 30% Off Your Order",
        "couponDescription": "Save 30% on gaming chairs and desk with this Ewin Racing code."
    },
    {
        "couponCode": "H20",
        "couponTitle": "EwinRacing Discount Code: 20% Off Your Order",
        "couponDescription": "Save 20% using this coupon code on your $359+ purchase at EwinRacing."
    },
    {
        "couponCode": "SEASONS25",
        "couponTitle": "Get Up to 25% Off Your Order ",
        "couponDescription": "Paste this promo code at checkout and save up to 25% on your order."
    },
    {
        "couponCode": "TECHAERIS",
        "couponTitle": "Take 20% Off Your Purchase",
        "couponDescription": "Save up to 20% on gaming chairs at Ewin Racing."
    },
    {
        "couponCode": "FRECKLES",
        "couponTitle": "Enjoy 20% Off Using Code",
        "couponDescription": "At checkout, apply 20% off with a promo code on your purchase at EwinRacing."
    },
    {
        "couponCode": "JakeRandall",
        "couponTitle": "Enjoy 30% Off at EwinRacing",
        "couponDescription": "Apply this promo code at checkout to take a 30% off on your entire online purchases today."
    },
    {
        "couponCode": "BASH",
        "couponTitle": "EwinRacing Coupon Code: 30% Off All Orders",
        "couponDescription": "With a code from EwinRacing, get an additional 30% off the Ewin Nexus Lucis RGB Gaming Desk with Wireless."
    },
    {
        "couponCode": "CW",
        "couponTitle": "Receive 25% Off Your Order Sitewide",
        "couponDescription": "Save 25% on your entire order at E-WIN with this exclusive coupon. Enjoy premium gaming chairs and accessories at a discounted price. Shop now and upgrade your setup for less."
    },
    {
        "couponCode": "BF",
        "couponTitle": "EwinRacing Coupon Code: Take 25% Off Your Purchase ",
        "couponDescription": "Enjoy a 25% discount on your purchase when you enter this coupon code at checkout."
    }
]