[
    {
        "couponCode": "HELLOPAULA",
        "couponTitle": "Save 10% Sitewide",
        "couponDescription": "Shop JTV if you love jewelry and use this promo code to get 10% off your order."
    },
    {
        "couponCode": "YESSAVE25",
        "couponTitle": "JTV Coupon: 15% Off Your Order",
        "couponDescription": "Save up to 10% on jewelry by adding this JTV code."
    },
    {
        "couponCode": "MERRYGIFT",
        "couponTitle": "JTV Promo Code: 20% Off Your Order",
        "couponDescription": "Take 20% off your purchase using a discount code on your cart."
    },
    {
        "couponCode": "JPK553XVFW",
        "couponTitle": "Take $25 Off Your Order",
        "couponDescription": "Enjoy extra $25 off sitewide when you spend $49 and more at JTV."
    },
    {
        "couponCode": "POWER25",
        "couponTitle": "Save $25 Off Your Purchase",
        "couponDescription": "Enter this JTV Jewelry promotional code during checkout to get a $25 discount on $150 total orders."
    },
    {
        "couponCode": "6D5M227Q55",
        "couponTitle": "JTV Discount Code: $25 Off Your Order",
        "couponDescription": "Save $25 on any order when you apply this promo code at checkout."
    },
    {
        "couponCode": "Y14KK89530",
        "couponTitle": "Get $25 Off Your Order",
        "couponDescription": "Enjoy $25 off when you spend $49 and more and free shipping with this JTV code."
    },
    {
        "couponCode": "HOPEFUL24",
        "couponTitle": "JTV Coupon: $5 Off Your Order",
        "couponDescription": "Save $5 on jewelry by adding this JTV code."
    },
    {
        "couponCode": "HN64TW2LTZ",
        "couponTitle": "JTV Discount Code: Take $25 Off Orders Over $49 Sitewide",
        "couponDescription": "Unlock a $25 discount on all orders over $49 at JTV. Make sure to apply this discount code during checkout. Shop sitewide and enjoy incredible savings today."
    },
    {
        "couponCode": "3CQQ3J26RW",
        "couponTitle": "JTV Jewelry Coupon: $25 Off Your Order",
        "couponDescription": "Don't forget to enter this discount code at checkout to receive $25 off on $49 or more total purchases."
    },
    {
        "couponCode": "3NWVMW1VL1",
        "couponTitle": "Get $25 Off Your Order",
        "couponDescription": "Enjoy $25 off when you purchase $49 and more at JTV."
    },
    {
        "couponCode": "JTV15MERRY",
        "couponTitle": "JTV Promo Code: 15% Off Your Order",
        "couponDescription": "Shop and take 15% off your purchase using a coupon code on your cart."
    },
    {
        "couponCode": "G35Y3L75L2",
        "couponTitle": "Take $25 Off Your Order",
        "couponDescription": "Get $25 off when you spend $49 and more at JTV."
    },
    {
        "couponCode": "R78M4P89PL",
        "couponTitle": "JTV Promo Code: $25 Off Your Order",
        "couponDescription": "Enjoy $25 off with minimum spend of $49 and more at JTV."
    },
    {
        "couponCode": "1D3PX7G548",
        "couponTitle": "Take $25 Off Orders $49+",
        "couponDescription": "Enjoy shopping and get a $25 discount on orders over $49 when you enter this coupon code at checkout."
    },
    {
        "couponCode": "TEXTSAVING",
        "couponTitle": "Up to 10% Off Sitewide at JTV Jewelry",
        "couponDescription": "Enjoy up to 10% off your total cart when you use this JTV Jewelry coupon code at checkout."
    },
    {
        "couponCode": "MERRY24",
        "couponTitle": "Take 65% Off Your Order",
        "couponDescription": "Big savings at JTV by getting up to 65% on select items."
    },
    {
        "couponCode": "NEW2JTV",
        "couponTitle": "JTV Coupon Code: 10% Off All Orders",
        "couponDescription": "Apply this coupon code at JTV to receive 10% off your order at checkout."
    },
    {
        "couponCode": "67XBZDG3WB",
        "couponTitle": "Get $25 Off Orders $49+ ",
        "couponDescription": "Paste this promo code at checkout and save $25 on orders over $49."
    },
    {
        "couponCode": "TJ704HVZWZ",
        "couponTitle": "$20 Off $49+ for New Customers",
        "couponDescription": "Use this JTV promo code at checkout and save $20 off $49+"
    }
]