[
    {
        "couponCode": "WHAL130FREE",
        "couponTitle": "Factor75 Promo Code: $130 Off + Free Shipping",
        "couponDescription": "Receive $130 off + free shipping on your first purchase with this discount code at Factor75."
    },
    {
        "couponCode": "COUPONFOLLOW276",
        "couponTitle": "Factor75 Coupon Code: Up to $276 Off ",
        "couponDescription": "Redeem this Factor75 promo code for up to $276 off, exclusively from CouponFollow."
    },
    {
        "couponCode": "Go130FREE",
        "couponTitle": "Factor75 Coupon: $130 Off Your Order",
        "couponDescription": "Take up to $130 off your purchase + free shipping on your first box with this Factor75 code."
    },
    {
        "couponCode": "FACTOR276",
        "couponTitle": "Score 60% Off Your Order with Factor75 Coupon Code",
        "couponDescription": "Take 60% off your total order when you apply this Factor75 promo code at checkout."
    },
    {
        "couponCode": "FACTORSE48367",
        "couponTitle": "Factor75 Coupon: Take $165 Off Any Purchase",
        "couponDescription": "Use a Factor75 coupon to receive $165 off plus free wellness shots for life."
    },
    {
        "couponCode": "BUSHY50",
        "couponTitle": "Take 50% Off Any Purchase ",
        "couponDescription": "Enjoy shopping and get a 50% discount on any purchase when you enter this coupon code at checkout."
    },
    {
        "couponCode": "FACTORSE59394",
        "couponTitle": "Take Up to $270 Off Any Purchase ",
        "couponDescription": "Enjoy shopping and get up to a $270 discount on any purchase when you enter this coupon code at checkout."
    },
    {
        "couponCode": "HS-B84VPGWI9",
        "couponTitle": "Score 50% Off Your Purchase",
        "couponDescription": "Use this Factor75 coupon to receive 50% off your first six boxes."
    },
    {
        "couponCode": "HS-ASHQMC2R0",
        "couponTitle": "Get $150 Off Your Purchase",
        "couponDescription": "Take $150 off your Factor75 order with this code."
    },
    {
        "couponCode": "HS-4ECV5N6L6",
        "couponTitle": "Get $150 Off Any Purchase",
        "couponDescription": "Big savings at Factor75 by getting $150 on your purchase."
    },
    {
        "couponCode": "FACTORSE6463",
        "couponTitle": "Factor75 Coupon Code: 50% Off Sitewide",
        "couponDescription": "Enter this promo code at checkout to get a 50% discount on your entire order."
    },
    {
        "couponCode": "FACTORSE55151",
        "couponTitle": "Get 50% Off Your Order",
        "couponDescription": "Save 50% on your first box with this Factor75 code."
    },
    {
        "couponCode": "SCYUM50KETO",
        "couponTitle": "Factor75 Coupon: 50% Off Your Order",
        "couponDescription": "Big savings at Factor75 by getting 50% on your purchase."
    },
    {
        "couponCode": "FIRSTFACTOR90",
        "couponTitle": "Enjoy $90 Off with Promo Code",
        "couponDescription": "Receive a $90 discount on your first three weeks by applying this coupon code at checkout."
    },
    {
        "couponCode": "DEEPDIVE50",
        "couponTitle": "Factor75 Discount Code: 50% Off",
        "couponDescription": "Save 50% using this coupon code for the first box on your purchase at Factor75."
    },
    {
        "couponCode": "FACTORSE15728",
        "couponTitle": "53% Off Fully-Prepared Food",
        "couponDescription": "Try out a new healthy meal delivery service. Factor75 is offering 53% your first order when you use this coupon code. Choose from a variety of delicious, chef-crafted meals that are all free of artificial ingredients, hormones, and antibiotics."
    },
    {
        "couponCode": "FACTOR130N",
        "couponTitle": "Factor75 Coupon: $130 Off Your Order",
        "couponDescription": "Get extra $130 off when you add this Factor75 code."
    },
    {
        "couponCode": "7O-W3GDF",
        "couponTitle": "Factor Coupon Code: 65% Off Your Order Instantly",
        "couponDescription": "Save on healthy fully-prepared meals. Get 65% off your purchase at Factor75.com when you use this discount code."
    },
    {
        "couponCode": "FACTOR60OFF",
        "couponTitle": "Factor75 Coupon Code: 60% Off Your Order",
        "couponDescription": "Take advantage of this 60% discount on your first order when you shop at factor75.com using this promo code. Limited-time offer."
    },
    {
        "couponCode": "FACTORSE58315",
        "couponTitle": "Factor75 Coupon: 50% Off Your Order",
        "couponDescription": "Save 50% on first box purchase with this Factor75 code."
    }
]