[
    {
        "couponCode": "YEAREND25",
        "couponTitle": "Save 25% Off Using Code",
        "couponDescription": "Get 25% off with code"
    },
    {
        "couponCode": "FiveOffSpecial",
        "couponTitle": "Enjoy $5 Discount On Your Total Purchase",
        "couponDescription": "$5 off entire order"
    },
    {
        "couponCode": "Great100",
        "couponTitle": "Complimentary Delivery For $100+ Purchases",
        "couponDescription": "FREE SHIPPING on orders $100+"
    },
    {
        "couponCode": "GIFT10",
        "couponTitle": "Christmas-Lights-Etc Coupon Code: 10% Off Your Order",
        "couponDescription": "Shop and receive 10% off your purchase using a discount code at checkout."
    },
    {
        "couponCode": "bf10",
        "couponTitle": "Enjoy Additional 10% Discount On Entire Purchase",
        "couponDescription": "Get an Extra 10% Off on Your Total Order"
    },
    {
        "couponCode": "SUPER100",
        "couponTitle": "September Sale: Up To 40% Off + Free Shipping",
        "couponDescription": "Save up to 40% off September Sale + Free Shipping over $100"
    },
    {
        "couponCode": "TRYAGAIN10",
        "couponTitle": "Get 10% Off Your Order",
        "couponDescription": "Take 10% off your Christmas-Lights-Etc purchase with this code."
    },
    {
        "couponCode": "WELCOME12",
        "couponTitle": "Christmas-Lights-Etc Coupon: 12% Off Your Order",
        "couponDescription": "Get 12% off christmas decorations at Christmas-Lights-Etc."
    },
    {
        "couponCode": "THANKS",
        "couponTitle": "Christmas-Lights-Etc Promo Code: Up To 40% Off + Free Shipping",
        "couponDescription": "Apply this Christmas-Lights-Etc coupon code at checkout to unlock up to 40% off plus free shipping of orders of $100 or more."
    },
    {
        "couponCode": "cyber20",
        "couponTitle": "Up to 10% Off With Code",
        "couponDescription": "Enjoy up to 10% off your cart using Christmas-Lights-Etc's discount code on your purchase."
    },
    {
        "couponCode": "CYBER100",
        "couponTitle": "Enjoy Up To 40% Discount On Your Order",
        "couponDescription": "Take Up to 40% Off on Your Purchase"
    },
    {
        "couponCode": "SNOWMAN",
        "couponTitle": "Free Shipping on Your Order",
        "couponDescription": "Shop and take free shipping on your purchase sitewide worth $100 using a promo code on your cart."
    },
    {
        "couponCode": "welcome10",
        "couponTitle": "Get 10% Off Your Purchase ",
        "couponDescription": "Enjoy an extra 10% off your order with this Christmas-Lights-Etc coupon code."
    },
    {
        "couponCode": "CLE241107P",
        "couponTitle": "10% Off Your Order",
        "couponDescription": "Shop and take 10% off your purchase using a promo code on your cart."
    },
    {
        "couponCode": "SHINE100",
        "couponTitle": "Christmas-Lights-Etc Coupon: Up to 40% Off Your Order + Free Delivery",
        "couponDescription": "Enjoy up to 40% off plus free shipping on orders over $100 using this promotional code at checkout."
    },
    {
        "couponCode": "BF15",
        "couponTitle": "Score 15% Off With Discount Code",
        "couponDescription": "Save 15% off your entire order with this Christmas Lights, Etc coupon code."
    },
    {
        "couponCode": "THANKS100",
        "couponTitle": "Complimentary Delivery For $100+ Purchases",
        "couponDescription": "Free Shipping on orders $100+"
    },
    {
        "couponCode": "SHINE150",
        "couponTitle": "Up to 40% Off Your Purchase + Free Shipping",
        "couponDescription": "When this Christmas-Lights-Etc coupon code is applied, you can receive up to 40% off plus free delivery on orders over $150."
    },
    {
        "couponCode": "deals10",
        "couponTitle": "Save 10% Off w/ Coupon Code",
        "couponDescription": "Score 10% off with discount code on $100+ orders"
    },
    {
        "couponCode": "CL171004AC",
        "couponTitle": "Enjoy 10% Discount Using Promo Code",
        "couponDescription": "Save 10% off with coupon code"
    }
]