[
    {
        "couponCode": "VHSC2LZOI",
        "couponTitle": "White Stuff Coupon Code: Take Extra $10 Off Orders $80+ ",
        "couponDescription": "Enjoy a $10 discount on orders of $80 or more when you enter this coupon code at checkout."
    },
    {
        "couponCode": "VKAXN1ZEN",
        "couponTitle": "White Stuff Promo Code: Extra 15% Off Your Order",
        "couponDescription": "Apply an additional 15% off at checkout when you purchase using this discount code for sitewide orders on your cart."
    },
    {
        "couponCode": "VHSAWQ6Y7",
        "couponTitle": "Take $10 Off Your Purchase",
        "couponDescription": "Enjoy $10 off when you spend $80 with this White Stuff code."
    },
    {
        "couponCode": "VCECBOQR6",
        "couponTitle": "White Stuff Coupon Code: Take Extra $10 Off Orders $90+ ",
        "couponDescription": "Enjoy an extra $10 discount on orders of $90 or more when you enter this coupon code at checkout."
    },
    {
        "couponCode": "LCDGRSNN9D5",
        "couponTitle": "Free Shipping with Code",
        "couponDescription": "Free shipping with discount code"
    },
    {
        "couponCode": "SMS1TU5FF",
        "couponTitle": "Get Up to 15% Off with Promo Code",
        "couponDescription": "Save up to 15% on your purchase when you enter this coupon code at checkout."
    },
    {
        "couponCode": "EXTRA20",
        "couponTitle": "Get Extra 20% Off Sale",
        "couponDescription": "Score an extra 20% off women's sale at White Stuff."
    },
    {
        "couponCode": "DMP44FY3G",
        "couponTitle": "Enjoy 15% Savings Using Promo Code",
        "couponDescription": "Score up to 15% off with coupon"
    },
    {
        "couponCode": "DOB15",
        "couponTitle": "Save 15% Off",
        "couponDescription": "Save 15% off with promo code"
    },
    {
        "couponCode": "WSEPT5",
        "couponTitle": "Extra 5% Off Your Order",
        "couponDescription": "Shop and get an extra 5% off your purchase using a promo code on your cart."
    },
    {
        "couponCode": "VCECWZG1I",
        "couponTitle": "White Stuff Coupon Code: Take $10 Off Orders $90+ ",
        "couponDescription": "Enjoy a $10 discount on orders of $90 or more when you enter this coupon code at checkout."
    },
    {
        "couponCode": "VKA5RL11F",
        "couponTitle": "Take 15% Off Your Order",
        "couponDescription": "Enjoy an extra 15% off sitewide by using this White Stuff code."
    },
    {
        "couponCode": "VKA6HJ1SX",
        "couponTitle": "15% Off Your Order",
        "couponDescription": "Shop and take 15% off your purchase using a promo code at checkout."
    },
    {
        "couponCode": "WS1085FPS",
        "couponTitle": "Get £10 Off Orders £85+ ",
        "couponDescription": "Paste this promo code at checkout and save £10 on orders of £85 or more."
    },
    {
        "couponCode": "WSAFF15",
        "couponTitle": "White Stuff Coupon Code: Save €15 on Orders Over €130",
        "couponDescription": "Use this White Stuff coupon code to save €15 on orders over €130. Shop now and enjoy great savings on your favorite items. Don't miss out on this limited-time offer."
    },
    {
        "couponCode": "LCDZZ9WE7",
        "couponTitle": "White Stuff Promo Code: Get 20% Off Any Order ",
        "couponDescription": "Redeem this prom code at checkout and save 20% on any order."
    },
    {
        "couponCode": "ETD3993G4",
        "couponTitle": "Enjoy 4% Discount Using Coupon Code",
        "couponDescription": "Take 4% off with coupon code"
    },
    {
        "couponCode": "VKA5NQQMH",
        "couponTitle": "White Stuff Discount Code: 15% Off Your Purchase",
        "couponDescription": "Shop and get 15% off your purchase using a promo code on your cart."
    },
    {
        "couponCode": "LNTZZ9UK9",
        "couponTitle": "Members Get $15 Off Select Orders $45 or More",
        "couponDescription": "Members get $15 off Rosie Cotton Maxi Dress orders at White Stuff when spending $45 or more. This coupon code must be used at checkout. Shop now to save on this stylish dress."
    },
    {
        "couponCode": "AFFWS5",
        "couponTitle": "Save Extra 5% on Any Purchase ",
        "couponDescription": "Shop at White Stuff and get an extra 5% discount on any purchase. Apply this discount code at checkout."
    }
]