[
    {
        "couponCode": "CONGRATS",
        "couponTitle": "Take Extra 10% Off Full Price Products",
        "couponDescription": "Shop now at Marimekko and receive an extra 10% discount on full-price products. Paste this discount code at checkout."
    },
    {
        "couponCode": "VIP10%",
        "couponTitle": "Marimekko Coupon: 10% Off Your Order",
        "couponDescription": "Receive 10% off when you use this Marimekko code."
    },
    {
        "couponCode": "FALLWINTER50",
        "couponTitle": "Take $50 Off w/ Coupon Code",
        "couponDescription": "Save $50 when you spend $200 using this Marimekko coupon code at checkout."
    },
    {
        "couponCode": "WELCOME10",
        "couponTitle": "Get 10% Savings Using Promo Code",
        "couponDescription": "Score up to 10% off with discount code"
    },
    {
        "couponCode": "HELLOSMS15",
        "couponTitle": " Marimekko Deals: Extra 15% Off Your Purchase Store-Wide",
        "couponDescription": "Save 15% off your cart when you use the Marimekko coupon code in your shopping cart at checkout."
    },
    {
        "couponCode": "MARICARTSMS",
        "couponTitle": "Save 28% Off w/ Discount Code",
        "couponDescription": "Score 28% off with code"
    },
    {
        "couponCode": "EXTRA20",
        "couponTitle": "Get 20% Reduction Using Promo Code",
        "couponDescription": "Save 20% off with discount code"
    },
    {
        "couponCode": "WELCOMESPRING",
        "couponTitle": "Get $100 Off $200+ Purchases Using Promo Code",
        "couponDescription": "enjoy $100 off on purchases worth $200+ with the promo code."
    },
    {
        "couponCode": "SEPT50LOYAL",
        "couponTitle": "Get $50 Off On $200+ Marimekko Orders",
        "couponDescription": "Spend $200 or more to receive an extra $50 off your order by using this Marimekko promo code at checkout."
    },
    {
        "couponCode": "PREFALL50",
        "couponTitle": "Take $50 Off",
        "couponDescription": "as a special treat, we're offering you $50 off your order of $200+ to celebrate the launch of our latest collection. use coupon code at checkout to redeem!"
    },
    {
        "couponCode": "SUMMERVIP",
        "couponTitle": "Marimekko Coupon: 50% Off Your Order",
        "couponDescription": "Big savings at Marimekko by getting 50% on your purchase."
    },
    {
        "couponCode": "SUMMER50",
        "couponTitle": "Get $50 Off $200+ New Marimekko Collection Orders",
        "couponDescription": "Take $50 off $200 or more in new collection orders by using this Marimekko coupon code at checkout."
    },
    {
        "couponCode": "SINGLES",
        "couponTitle": "Enjoy 20% Discount At Marimekko With Code",
        "couponDescription": "marimekko: get 20% off with coupon code"
    },
    {
        "couponCode": "JINGLE20",
        "couponTitle": "Save 20% Off Using Code",
        "couponDescription": "marimekko: shop 20% off bags with coupon code"
    },
    {
        "couponCode": "SPRING50",
        "couponTitle": "Take $50 Off",
        "couponDescription": "Save $50 off your full-price purchase of $200 or more at marimekko.com."
    },
    {
        "couponCode": "FRIEND20",
        "couponTitle": "Save 20% Off",
        "couponDescription": "Save 20% off any full-price purchase at marimekko.com."
    },
    {
        "couponCode": "to",
        "couponTitle": "Enjoy 10% Discount Using Promo Code",
        "couponDescription": "Score 10% off with code"
    },
    {
        "couponCode": "WELCOME15",
        "couponTitle": "Enjoy 15% Discount On All Items",
        "couponDescription": "Save 15% off All Purchases"
    },
    {
        "couponCode": "JINGLE",
        "couponTitle": "Save 20% Off using Coupon Code",
        "couponDescription": "Receive 20% off on Bags"
    }
]